sotastream/__init__.py
sotastream/__main__.py
sotastream/cli.py
sotastream/data.py
sotastream/augmentors/__init__.py
sotastream/augmentors/augmentors.py
sotastream/filters/__init__.py
sotastream/filters/filters.py
sotastream/pipelines/__init__.py
sotastream/pipelines/base.py
sotastream/pipelines/default.py
sotastream/pipelines/example_pipeline.py
sotastream/pipelines/mtdata_pipeline.py
sotastream/pipelines/multistream_pipeline.py
sotastream/utils/__init__.py
sotastream/utils/phrases.py
sotastream/utils/split.py
sotastream-1.0.1.dist-info/LICENSE
sotastream-1.0.1.dist-info/METADATA
sotastream-1.0.1.dist-info/WHEEL
sotastream-1.0.1.dist-info/entry_points.txt
sotastream-1.0.1.dist-info/top_level.txt
sotastream-1.0.1.dist-info/RECORD
