Metadata-Version: 2.1
Name: sotastream
Version: 1.0.1
Summary: Sotastream is a command line tool that augments a batch of text and produces infinite stream of records.
Author-email: "Text MT @ Microsoft Translator" <marcinjd@microsoft.com>
Maintainer-email: Thamme Gowda <thammegowda@microsoft.com>, Roman Grundkiewicz <roman.grundkiewicz@microsoft.com>, Matt Post <mattpost@microsoft.com>
Project-URL: homepage, https://github.com/marian-nmt/sotastream
Project-URL: documentation, https://github.com/marian-nmt/sotastream
Project-URL: repository, https://github.com/marian-nmt/sotastream
Keywords: data augmentation,machine translation,natural language processing,text processing,text augmentation,machine learning,deep learning,artificial intelligence
Classifier: Development Status :: 4 - Beta
Classifier: Programming Language :: Python
Requires-Python: >=3.6
License-File: LICENSE
Requires-Dist: titlecase
Requires-Dist: infinibatch
Requires-Dist: sentencepiece
Requires-Dist: mtdata >=0.4.0
Provides-Extra: dev
Requires-Dist: black ; extra == 'dev'
Requires-Dist: sphinx ; extra == 'dev'
Requires-Dist: sphinx-rtd-theme ; extra == 'dev'
Provides-Extra: test
Requires-Dist: pytest <5.0.0 ; extra == 'test'
Requires-Dist: pytest-cov[all] ; extra == 'test'
